{"skeleton":{"hash":"yZaUfCMToZ6JJmcvE6FFyucG0As","spine":"3.3.07","width":347,"height":123.99,"images":"./whale/"},"bones":[{"name":"root"},{"name":"bone","parent":"root","y":-0.67},{"name":"bone2","parent":"bone","length":106.15,"rotation":167.73,"x":-4.5,"y":3.15},{"name":"bone3","parent":"bone2","length":62.2,"rotation":-4.59,"x":149.34,"y":-11.84},{"name":"bone4","parent":"bone","length":81.32,"rotation":-135.67,"x":10.37,"y":4.96},{"name":"bone5","parent":"bone","length":50.53,"rotation":-57.01,"x":12.17,"y":0.9},{"name":"bone6","parent":"bone","length":9.48,"rotation":177.27,"x":49.15,"y":21.19}],"slots":[{"name":"01qi","bone":"bone5","attachment":"01qi"},{"name":"02forktail","bone":"bone3","attachment":"02forktail"},{"name":"03boby","bone":"bone2","attachment":"03boby"},{"name":"04head","bone":"bone","attachment":"04head"},{"name":"05zuiba","bone":"bone","attachment":"05zuiba"},{"name":"06line","bone":"bone","attachment":"06line"},{"name":"07qi","bone":"bone4","attachment":"07qi"},{"name":"08eyes","bone":"bone","attachment":"08eyes"},{"name":"09eyes","bone":"bone6","attachment":"09eyes"}],"skins":{"default":{"01qi":{"01qi":{"x":21.43,"y":-4.85,"rotation":57.01,"width":44,"height":48}},"02forktail":{"02forktail":{"x":29.44,"y":3.87,"rotation":-163.14,"width":60,"height":40}},"03boby":{"03boby":{"x":65.33,"y":1.79,"rotation":-167.73,"width":179,"height":84}},"04head":{"04head":{"x":50.76,"y":12.27,"width":178,"height":78}},"05zuiba":{"05zuiba":{"x":58.76,"y":10.77,"width":162,"height":75}},"06line":{"06line":{"x":64.26,"y":12.27,"width":143,"height":72}},"07qi":{"07qi":{"x":38.42,"y":-3.03,"rotation":135.67,"width":72,"height":66}},"08eyes":{"08eyes":{"x":43.76,"y":21.27,"width":10,"height":10}},"09eyes":{"09eyes":{"x":3.39,"y":0.07,"rotation":-177.27,"width":6,"height":6}}}},"animations":{"animation":{},"youdong":{"bones":{"bone6":{"rotate":[{"time":0,"angle":-1.83}],"translate":[{"time":0,"x":0,"y":0,"curve":"stepped"},{"time":1,"x":0,"y":0},{"time":1.5,"x":-4.51,"y":-0.37},{"time":2,"x":0,"y":0,"curve":"stepped"},{"time":3.3333,"x":0,"y":0},{"time":3.8,"x":-4.51,"y":-0.37},{"time":4.3333,"x":0,"y":0}],"scale":[{"time":0,"x":1,"y":1}]},"bone5":{"rotate":[{"time":0,"angle":-1.83},{"time":1,"angle":-73.17},{"time":2,"angle":-1.83,"curve":"stepped"},{"time":2.3333,"angle":-1.83},{"time":3.3333,"angle":-73.17},{"time":4.3333,"angle":-1.83}],"translate":[{"time":0,"x":0,"y":0,"curve":"stepped"},{"time":2,"x":0,"y":0,"curve":"stepped"},{"time":2.3333,"x":0,"y":0,"curve":"stepped"},{"time":4.3333,"x":0,"y":0}],"scale":[{"time":0,"x":1,"y":1},{"time":1,"x":0.908,"y":0.908},{"time":2,"x":1,"y":1,"curve":"stepped"},{"time":2.3333,"x":1,"y":1},{"time":3.3333,"x":0.908,"y":0.908,"curve":"stepped"},{"time":4.3333,"x":0.908,"y":0.908}]},"bone4":{"rotate":[{"time":0,"angle":-1.83},{"time":1,"angle":-22.61},{"time":2,"angle":-1.83,"curve":"stepped"},{"time":2.3333,"angle":-1.83},{"time":3.3333,"angle":-22.61},{"time":4.3333,"angle":-1.83}],"translate":[{"time":0,"x":0,"y":0,"curve":"stepped"},{"time":2,"x":0,"y":0,"curve":"stepped"},{"time":2.3333,"x":0,"y":0,"curve":"stepped"},{"time":4.3333,"x":0,"y":0}],"scale":[{"time":0,"x":1,"y":1},{"time":1,"x":0.873,"y":0.873},{"time":2,"x":1,"y":1,"curve":"stepped"},{"time":2.3333,"x":1,"y":1,"curve":"stepped"},{"time":3.3333,"x":1,"y":1},{"time":4.3333,"x":0.873,"y":0.873}]},"bone3":{"rotate":[{"time":0,"angle":-1.83},{"time":1,"angle":-28.09},{"time":2,"angle":-1.83,"curve":"stepped"},{"time":2.3333,"angle":-1.83},{"time":3.3333,"angle":-28.09},{"time":4.3333,"angle":-1.83}],"translate":[{"time":0,"x":0,"y":0,"curve":"stepped"},{"time":2.3333,"x":0,"y":0}],"scale":[{"time":0,"x":1,"y":1,"curve":"stepped"},{"time":2.3333,"x":1,"y":1}]},"bone2":{"rotate":[{"time":0,"angle":-1.83},{"time":1,"angle":9.72},{"time":2,"angle":-1.83,"curve":"stepped"},{"time":2.3333,"angle":-1.83},{"time":3.3333,"angle":9.72},{"time":4.3333,"angle":-1.83}],"translate":[{"time":0,"x":0,"y":0,"curve":"stepped"},{"time":2,"x":0,"y":0,"curve":"stepped"},{"time":2.3333,"x":0,"y":0,"curve":"stepped"},{"time":4.3333,"x":0,"y":0}],"scale":[{"time":0,"x":1,"y":1},{"time":1,"x":0.931,"y":1},{"time":2,"x":1,"y":1,"curve":"stepped"},{"time":2.3333,"x":1,"y":1},{"time":3.3333,"x":0.931,"y":1},{"time":4.3333,"x":1,"y":1}]}}}}}